<annotation>
	<folder>JPEGImages</folder>
	<filename>167.png</filename>
	<path>C:/Users/admin/Desktop/resume_dataset/JPEGImages/167.png</path>
	<source>
		<database>Unknown</database>
	</source>
	<size>
		<width>1309</width>
		<height>1852</height>
		<depth>3</depth>
	</size>
	<segmented>0</segmented>
	<object>
		<name>name</name>
		<pose>Unspecified</pose>
		<truncated>0</truncated>
		<difficult>0</difficult>
		<bndbox>
			<xmin>335</xmin>
			<ymin>50</ymin>
			<xmax>977</xmax>
			<ymax>152</ymax>
		</bndbox>
	</object>
	<object>
		<name>personal information</name>
		<pose>Unspecified</pose>
		<truncated>0</truncated>
		<difficult>0</difficult>
		<bndbox>
			<xmin>209</xmin>
			<ymin>212</ymin>
			<xmax>1113</xmax>
			<ymax>260</ymax>
		</bndbox>
	</object>
	<object>
		<name>work experience</name>
		<pose>Unspecified</pose>
		<truncated>0</truncated>
		<difficult>0</difficult>
		<bndbox>
			<xmin>55</xmin>
			<ymin>366</ymin>
			<xmax>1251</xmax>
			<ymax>752</ymax>
		</bndbox>
	</object>
	<object>
		<name>education</name>
		<pose>Unspecified</pose>
		<truncated>0</truncated>
		<difficult>0</difficult>
		<bndbox>
			<xmin>55</xmin>
			<ymin>848</ymin>
			<xmax>1261</xmax>
			<ymax>1120</ymax>
		</bndbox>
	</object>
	<object>
		<name>certificates</name>
		<pose>Unspecified</pose>
		<truncated>0</truncated>
		<difficult>0</difficult>
		<bndbox>
			<xmin>51</xmin>
			<ymin>1212</ymin>
			<xmax>1271</xmax>
			<ymax>1328</ymax>
		</bndbox>
	</object>
	<object>
		<name>work experience</name>
		<pose>Unspecified</pose>
		<truncated>0</truncated>
		<difficult>0</difficult>
		<bndbox>
			<xmin>51</xmin>
			<ymin>1418</ymin>
			<xmax>1259</xmax>
			<ymax>1608</ymax>
		</bndbox>
	</object>
</annotation>
